block_io/__init__.py
block_io/bitcoinutils_patches.py
block_io/pbkdf2.py
block_io-2.0.6.dist-info/LICENSE
block_io-2.0.6.dist-info/METADATA
block_io-2.0.6.dist-info/WHEEL
block_io-2.0.6.dist-info/top_level.txt
block_io-2.0.6.dist-info/RECORD
