Metadata-Version: 2.1
Name: block-io
Version: 2.0.6
Summary: The easiest way to integrate Bitcoin, Dogecoin and Litecoin in your applications. Sign up at Block.io for your API key.
Home-page: https://github.com/BlockIo/block_io-python
Author: Atif Nazir
Author-email: a@block.io
License: MIT
Requires-Python: >=3.6, <4
License-File: LICENSE
